.long-description.html
README.rst
setup.py
src/collective/__init__.py
src/collective.searchevent.egg-info/PKG-INFO
src/collective.searchevent.egg-info/SOURCES.txt
src/collective.searchevent.egg-info/dependency_links.txt
src/collective.searchevent.egg-info/entry_points.txt
src/collective.searchevent.egg-info/namespace_packages.txt
src/collective.searchevent.egg-info/not-zip-safe
src/collective.searchevent.egg-info/requires.txt
src/collective.searchevent.egg-info/top_level.txt
src/collective/searchevent/__init__.py
src/collective/searchevent/collection.py
src/collective/searchevent/configure.zcml
src/collective/searchevent/interfaces.py
src/collective/searchevent/schema.py
src/collective/searchevent/upgrades.py
src/collective/searchevent/upgrades.zcml
src/collective/searchevent/utility.py
src/collective/searchevent/vocabulary.py
src/collective/searchevent/Extensions/Install.py
src/collective/searchevent/Extensions/__init__.py
src/collective/searchevent/adapter/__init__.py
src/collective/searchevent/adapter/configure.zcml
src/collective/searchevent/adapter/interface.py
src/collective/searchevent/adapter/listing.py
src/collective/searchevent/browser/__init__.py
src/collective/searchevent/browser/configure.zcml
src/collective/searchevent/browser/interfaces.py
src/collective/searchevent/browser/template.py
src/collective/searchevent/browser/viewlet.py
src/collective/searchevent/browser/static/css/main.css
src/collective/searchevent/browser/templates/controlpanel.pt
src/collective/searchevent/browser/viewlets/export.pt
src/collective/searchevent/browser/viewlets/search-event-results.pt
src/collective/searchevent/docs/CREDITS.rst
src/collective/searchevent/docs/HISTORY.rst
src/collective/searchevent/docs/LICENSE.rst
src/collective/searchevent/docs/README.rst
src/collective/searchevent/locales/collective.searchevent.pot
src/collective/searchevent/locales/fi/LC_MESSAGES/collective.searchevent.mo
src/collective/searchevent/locales/fi/LC_MESSAGES/collective.searchevent.po
src/collective/searchevent/portlets/__init__.py
src/collective/searchevent/portlets/configure.zcml
src/collective/searchevent/portlets/formwrapper.pt
src/collective/searchevent/portlets/search.pt
src/collective/searchevent/portlets/search.py
src/collective/searchevent/profiles/default/controlpanel.xml
src/collective/searchevent/profiles/default/cssregistry.xml
