Metadata-Version: 1.1
Name: collective.searchevent
Version: 0.6.1
Summary: Adds portlet to search event content types for Plone.
Home-page: https://github.com/collective/collective.searchevent
Author: Taito Horiuchi
Author-email: taito.horiuchi@gmail.com
License: BSD
Platform: UNKNOWN
Classifier: Framework :: Plone
Classifier: Framework :: Plone :: 4.3
Classifier: License :: OSI Approved :: BSD License
Classifier: Programming Language :: Python
Classifier: Programming Language :: Python :: 2.7
